{
  "schema_version": "real-oss-source-provenance/v2",
  "slug": "inkscape-inkweb",
  "project": "Inkscape InkWeb JavaScript",
  "source_root": "/usr/share/inkscape/extensions",
  "snapshot_path": "/mnt/data/audit_js_end/Js-End/fixtures/oss-replay/real-local-oss10/inkscape-inkweb",
  "dpkg_owner": "",
  "copied_files": [
    "inkweb.js",
    "LICENSE.txt",
    "index.html"
  ],
  "missing_files": [],
  "file_hashes": [
    {
      "path": "inkweb.js",
      "sha256": "2ad806e9c0587fdca1efea302f4505e1c4d717566c944d11521fecda27d21028",
      "size": 7628
    },
    {
      "path": "LICENSE.txt",
      "sha256": "640d90f6ee401241ff62834d0d1b33f83049e99b8bfdfa04ed1b0a1635dde3e7",
      "size": 18093
    },
    {
      "path": "index.html",
      "sha256": "d52d40ef609940a38ff71b95f549c1aafeedc62e366567f36f86da577f1d371d",
      "size": 113
    }
  ],
  "license_or_copyright_file": "LICENSE.txt",
  "note": "Local installed open-source package/source subset copied for deterministic static replay. This is not a user authorized web target runtime replay."
}